odoo/addons/stock_dropshipping_whole_supplier/README.rst
odoo/addons/stock_dropshipping_whole_supplier/__init__.py
odoo/addons/stock_dropshipping_whole_supplier/__manifest__.py
odoo/addons/stock_dropshipping_whole_supplier/demo/stock.xml
odoo/addons/stock_dropshipping_whole_supplier/i18n/fr.po
odoo/addons/stock_dropshipping_whole_supplier/i18n/pt_BR.po
odoo/addons/stock_dropshipping_whole_supplier/i18n/stock_dropshipping_whole_supplier.pot
odoo/addons/stock_dropshipping_whole_supplier/models/__init__.py
odoo/addons/stock_dropshipping_whole_supplier/models/partner.py
odoo/addons/stock_dropshipping_whole_supplier/models/sale.py
odoo/addons/stock_dropshipping_whole_supplier/readme/CONTRIBUTORS.rst
odoo/addons/stock_dropshipping_whole_supplier/readme/DESCRIPTION.rst
odoo/addons/stock_dropshipping_whole_supplier/readme/USAGE.rst
odoo/addons/stock_dropshipping_whole_supplier/static/description/icon.png
odoo/addons/stock_dropshipping_whole_supplier/static/description/index.html
odoo/addons/stock_dropshipping_whole_supplier/tests/__init__.py
odoo/addons/stock_dropshipping_whole_supplier/tests/test_whole_dropshipping.py
odoo/addons/stock_dropshipping_whole_supplier/views/partner.xml
odoo12_addon_stock_dropshipping_whole_supplier-12.0.1.0.0.99.dev10.dist-info/METADATA
odoo12_addon_stock_dropshipping_whole_supplier-12.0.1.0.0.99.dev10.dist-info/WHEEL
odoo12_addon_stock_dropshipping_whole_supplier-12.0.1.0.0.99.dev10.dist-info/top_level.txt
odoo12_addon_stock_dropshipping_whole_supplier-12.0.1.0.0.99.dev10.dist-info/RECORD
